<?xml version = '1.0' encoding = 'UTF-8'?>
<SegmentOraclev10g class="oracle.dbtools.crest.model.design.storage.oracle.v10g.SegmentOraclev10g" name="Storage1" directorySegmentName="seg_0" id="4AEA6F1B-4827-BE2B-A487-EA37FBCF363F">
<createdBy>im</createdBy>
<createdTime>2015-10-25 09:10:29 UTC</createdTime>
<ownerDesignName>icu</ownerDesignName>
<maxTrans>255</maxTrans>
<scInitialExtent>65536</scInitialExtent>
<scMaxExtents>2147483645</scMaxExtents>
<scNextExtent>1048576</scNextExtent>
</SegmentOraclev10g>